sigmaSMSApi/__init__.py
sigmaSMSApi/exceptions.py
sigmaSMSApi/models.py
sigmaSMSApi/sigmasms.py
sigmaSMSApi-0.5.2.dist-info/LICENSE.txt
sigmaSMSApi-0.5.2.dist-info/METADATA
sigmaSMSApi-0.5.2.dist-info/WHEEL
sigmaSMSApi-0.5.2.dist-info/top_level.txt
sigmaSMSApi-0.5.2.dist-info/RECORD
