Metadata-Version: 2.1
Name: sigmaSMSApi
Version: 0.5.2
Summary: Tool for integration with SigmaSMS API
Home-page: https://github.com/KristinaErdman/sigmaSMSApi
Download-URL: https://github.com/KristinaErdman/sigmaSMSApi/archive/refs/tags/0.3.0.tar.gz
Author: Tabunchik (Erdman) Kristina
Author-email: erdmakristina8@gmail.com
License: MIT
Keywords: sigmaSMS,SMS
License-File: LICENSE.txt
Requires-Dist: requests
